Mock/GPIO.py
Mock/__init__.py
mock_gpio-0.2.0.dist-info/licenses/LICENSE
mock_gpio-0.2.0.dist-info/METADATA
mock_gpio-0.2.0.dist-info/WHEEL
mock_gpio-0.2.0.dist-info/top_level.txt
mock_gpio-0.2.0.dist-info/RECORD
